ssm/__init__.py
ssm/cstats.cpython-36m-darwin.so
ssm/emissions.py
ssm/hierarchical.py
ssm/hmm.py
ssm/init_state_distns.py
ssm/lds.py
ssm/messages.cpython-36m-darwin.so
ssm/model_selection.py
ssm/observations.py
ssm/optimizers.py
ssm/preprocessing.py
ssm/primitives.py
ssm/stats.py
ssm/transitions.py
ssm/util.py
ssm/variational.py
ssm-0.0.1.dist-info/LICENSE
ssm-0.0.1.dist-info/METADATA
ssm-0.0.1.dist-info/WHEEL
ssm-0.0.1.dist-info/top_level.txt
ssm-0.0.1.dist-info/RECORD
