Metadata-Version: 2.1
Name: ssm
Version: 0.0.1
Summary: Bayesian learning and inference for a variety of state space models
Home-page: https://github.com/slinderman/ssm
Author: Scott Linderman
Author-email: scott.linderman@stanford.edu
License: UNKNOWN
Platform: UNKNOWN
Requires-Dist: numpy
Requires-Dist: scipy
Requires-Dist: matplotlib
Requires-Dist: scikit-learn
Requires-Dist: tqdm
Requires-Dist: autograd
